[
  {"region":"Granada","site":"Winter Hill","pol":"H","lat":0.935942502716178,"lng":-0.043891439339526,"power":100},
  {"region":"Yorkshire","site":"Stocksbridge","pol":"V","lat":0.933549179337468,"lng":-2.76907355191785E-02,"power":0.0024},
  {"region":"Granada","site":"Darwen","pol":"V","lat":0.937182103121994,"lng":-0.042643031376982,"power":0.1},
  {"region":"Yorkshire","site":"Holmfield","pol":"V","lat":0.938318338242999,"lng":-3.25761925637621E-02,"power":0.0044},
  {"region":"Granada","site":"Woodnook","pol":"V","lat":0.938041872769855,"lng":-0.041209763141565,"power":0.002},
  {"region":"Yorkshire","site":"Cleckheaton","pol":"V","lat":0.937532804411126,"lng":-3.00583602198169E-02,"power":0.002},
  {"region":"Central","site":"Earl Sterndale","pol":"V","lat":0.928464823875416,"lng":-3.25676753303767E-02,"power":0.04},
  {"region":"Yorkshire","site":"Oxenhope","pol":"V","lat":0.938997185987243,"lng":-3.41851707204022E-02,"power":0.04},
  {"region":"Yorkshire","site":"Oughtibridge","pol":"V","lat":0.932932696178345,"lng":-2.68478026885856E-02,"power":0.0078},
  {"region":"Yorkshire","site":"Calver Peak","pol":"V","lat":0.929652826697833,"lng":-2.88613735095154E-02,"power":0.05},
  {"region":"Granada","site":"Congleton","pol":"V","lat":0.927713182489665,"lng":-3.84553558388428E-02,"power":0.04},
  {"region":"Granada","site":"Blackburn","pol":"V","lat":0.93800669807536,"lng":-4.27919678506627E-02,"power":0.004},
  {"region":"Central","site":"Ashford In The Water","pol":"V","lat":0.928843113673835,"lng":-2.99814034076138E-02,"power":0.0028},
  {"region":"Granada","site":"Over Biddulph","pol":"V","lat":0.927501053342735,"lng":-3.76376811615479E-02,"power":0.0044},
  {"region":"Yorkshire","site":"Grenoside","pol":"H","lat":0.932628946890628,"lng":-2.62153213374452E-02,"power":1},
  {"region":"Yorkshire","site":"Batley","pol":"V","lat":0.937593237986786,"lng":-0.028600657224672,"power":0.0025},
  {"region":"Granada","site":"Trawden","pol":"V","lat":0.939621792647568,"lng":-3.73432618973001E-02,"power":0.04},
  {"region":"Yorkshire","site":"Sheffield","pol":"V","lat":0.931646147304695,"lng":-2.64209383894997E-02,"power":1},
  {"region":"Granada","site":"Brinscall","pol":"V","lat":0.937171872350092,"lng":-4.47073735658694E-02,"power":0.002},
  {"region":"Yorkshire","site":"Bradford West","pol":"V","lat":0.939113595129883,"lng":-3.13969348026153E-02,"power":0.0025},
  {"region":"Yorkshire","site":"Cullingworth","pol":"H","lat":0.939674051166638,"lng":-3.29273030764856E-02,"power":0.0026},
  {"region":"Granada","site":"Pendle Forest","pol":"V","lat":0.939709028707713,"lng":-3.95557070318752E-02,"power":0.1},
  {"region":"Yorkshire","site":"Totley Rise","pol":"V","lat":0.930648673320992,"lng":-2.64951587297477E-02,"power":0.016},
  {"region":"Central","site":"Hartington","pol":"V","lat":0.927439443496119,"lng":-3.18612242346082E-02,"power":0.0066},
  {"region":"Granada","site":"Whalley","pol":"V","lat":0.939213991788812,"lng":-4.20919173223242E-02,"power":0.01},
  {"region":"Central","site":"Leek","pol":"V","lat":0.926812549159807,"lng":-3.49423698768985E-02,"power":0.2},
  {"region":"Yorkshire","site":"Keighley Town","pol":"V","lat":0.94006019224661,"lng":-3.32075570527105E-02,"power":0.002},
  {"region":"Granada","site":"Moss Bank","pol":"V","lat":0.933253272323706,"lng":-4.78371093157631E-02,"power":0.008},
  {"region":"Yorkshire","site":"Idle","pol":"V","lat":0.939560715476961,"lng":-3.05806546163554E-02,"power":0.05},
  {"region":"Yorkshire","site":"Blackburn In Rotherham","pol":"V","lat":0.932507628912356,"lng":-2.47142448793239E-02,"power":0.002},
  {"region":"Yorkshire","site":"Sutton In Craven","pol":"V","lat":0.940421670897202,"lng":-3.48130202813526E-02,"power":0.0024},
  {"region":"Yorkshire","site":"Wincobank","pol":"V","lat":0.932401033495925,"lng":-2.47314631496405E-02,"power":0.002},
  {"region":"Yorkshire","site":"Cowling","pol":"V","lat":0.940482688794777,"lng":-3.57264234834244E-02,"power":0.0026},
  {"region":"Granada","site":"Skelmersdale","pol":"H","lat":0.934808372788739,"lng":-4.80223705579997E-02,"power":0.1},
  {"region":"Yorkshire","site":"Dronfield","pol":"H","lat":0.930407166189496,"lng":-2.54213281050782E-02,"power":0.002},
  {"region":"Central","site":"Stanton Moor","pol":"V","lat":0.927991956506152,"lng":-2.85196648790238E-02,"power":0.4},
  {"region":"Yorkshire","site":"Beecroft Hill","pol":"V","lat":0.939188752023542,"lng":-0.028645267732711,"power":0.2},
  {"region":"Yorkshire","site":"Keighley","pol":"V","lat":0.940654632122567,"lng":-3.31025998558704E-02,"power":2},
  {"region":"Central","site":"Birchover","pol":"H","lat":0.927664396493032,"lng":-2.86294479650259E-02,"power":0.005},
  {"region":"Central","site":"Darley Dale","pol":"V","lat":0.928067854603711,"lng":-2.77382834941118E-02,"power":0.0032},
  {"region":"Granada","site":"Parbold","pol":"V","lat":0.935415675487536,"lng":-4.87240682874018E-02,"power":0.06},
  {"region":"Yorkshire","site":"Chesterfield","pol":"V","lat":0.92998120327464,"lng":-2.49136315885257E-02,"power":0.8},
  {"region":"Central","site":"Ipstones Edge","pol":"V","lat":0.925952513455029,"lng":-3.38096670564799E-02,"power":0.0056},
  {"region":"Granada","site":"Chatburn","pol":"V","lat":0.940677423709921,"lng":-4.11634274747598E-02,"power":0.002},
  {"region":"Granada","site":"Walton Le Dale","pol":"H","lat":0.938233020126273,"lng":-4.69769220029945E-02,"power":0.004},
  {"region":"Central","site":"Parwich","pol":"V","lat":0.926504213615158,"lng":-3.01035343280415E-02,"power":0.002},
  {"region":"Yorkshire","site":"Brockwell","pol":"V","lat":0.929086630590343,"lng":-2.51765792359952E-02,"power":0.002},
  {"region":"Yorkshire","site":"Headingley","pol":"H","lat":0.939346294450269,"lng":-2.69895958125612E-02,"power":0.0024},
  {"region":"Yorkshire","site":"Addingham","pol":"V","lat":0.941412126938872,"lng":-3.29146277345916E-02,"power":0.0046},
  {"region":"Yorkshire","site":"Skipton Town","pol":"V","lat":0.941689150703741,"lng":-3.49804238812304E-02,"power":0.0026},
  {"region":"Granada","site":"Chaigley","pol":"V","lat":0.940673198927169,"lng":-4.32722371267373E-02,"power":0.008},
  {"region":"Central","site":"Matlock","pol":"V","lat":0.92723432230811,"lng":-2.71724090550746E-02,"power":0.0034},
  {"region":"Yorkshire","site":"Skipton","pol":"V","lat":0.941800653243607,"lng":-3.73611900447254E-02,"power":2},
  {"region":"Central","site":"Fenton","pol":"V","lat":0.925078920633162,"lng":-3.74572475184416E-02,"power":2},
  {"region":"Yorkshire","site":"Hasland","pol":"V","lat":0.928925436138933,"lng":-2.42950835144093E-02,"power":0.002},
  {"region":"Granada","site":"Elton","pol":"V","lat":0.929492207931461,"lng":-4.91219528981476E-02,"power":0.0126},
  {"region":"Central","site":"Oakamoor","pol":"V","lat":0.92500310715025,"lng":-3.34469653898007E-02,"power":0.0022},
  {"region":"Central","site":"Bolehill","pol":"V","lat":0.926671392260685,"lng":-2.72537735699341E-02,"power":0.1},
  {"region":"Yorkshire","site":"Wharfedale","pol":"V","lat":0.941295163573045,"lng":-2.96692556708881E-02,"power":0.4},
  {"region":"Central","site":"Cheadle","pol":"V","lat":0.924830898049771,"lng":-3.41414816755215E-02,"power":0.0048},
  {"region":"Yorkshire","site":"Conisbrough","pol":"V","lat":0.93333884624059,"lng":-0.021360495306394,"power":0.002},
  {"region":"Central","site":"Ashbourne","pol":"V","lat":0.925221076438721,"lng":-3.02001364829313E-02,"power":0.05},
  {"region":"Central","site":"Ambergate","pol":"V","lat":0.926039398786558,"lng":-2.57680188261226E-02,"power":0.037},
  {"region":"Granada","site":"Storeton","pol":"V","lat":0.931130630306091,"lng":-5.29078058123868E-02,"power":0.56},
  {"region":"Wales","site":"Storeton Wales","pol":"H","lat":0.931130630306091,"lng":-5.29078058123868E-02,"power":3},
  {"region":"Central","site":"Belper","pol":"V","lat":0.925242520600657,"lng":-2.61626673642976E-02,"power":0.006},
  {"region":"Yorkshire","site":"Grassington","pol":"V","lat":0.943720503674816,"lng":-3.45219042674488E-02,"power":0.012},
  {"region":"Yorkshire","site":"Heyshaw","pol":"V","lat":0.943591748704587,"lng":-3.03807166131494E-02,"power":0.1},
  {"region":"Granada","site":"Sunningdale","pol":"V","lat":0.931973516895072,"lng":-5.40936644993147E-02,"power":0.12},
  {"region":"Yorkshire","site":"Kettlewell","pol":"V","lat":0.944366777862966,"lng":-3.52610065609255E-02,"power":0.026},
  {"region":"Granada","site":"Austwick","pol":"V","lat":0.944233301652629,"lng":-4.07056505547684E-02,"power":0.0063},
  {"region":"Central","site":"Little Eaton","pol":"V","lat":0.92456081177708,"lng":-0.025273878809706,"power":0.004},
  {"region":"Central","site":"Eastwood","pol":"V","lat":0.92534370259403,"lng":-2.28676843113882E-02,"power":0.002},
  {"region":"Granada","site":"West Kirby","pol":"V","lat":0.931428767207178,"lng":-5.52862350397522E-02,"power":0.015},
  {"region":"Central","site":"Derby Uttoxeter Road","pol":"H","lat":0.923478431212195,"lng":-2.63932463501457E-02,"power":0.04},
  {"region":"Granada","site":"Ribblesdale","pol":"V","lat":0.944972649263585,"lng":-3.98886868759527E-02,"power":0.006},
  {"region":"Yorkshire","site":"Bilbrough","pol":"H","lat":0.941049971277412,"lng":-0.020516383122894,"power":8},
  {"region":"Central","site":"Nottingham","pol":"V","lat":0.924794647130055,"lng":-2.18416797234609E-02,"power":0.4},
  {"region":"Wales","site":"Wrexham Rhos","pol":"V","lat":0.926355902551326,"lng":-5.31451764948418E-02,"power":0.08},
  {"region":"Granada","site":"Far Highfield","pol":"H","lat":0.944199454538587,"lng":-4.71293770022974E-02,"power":0.0028},
  {"region":"Granada","site":"Melling HP","pol":"H","lat":0.944706901944842,"lng":-4.55461580210709E-02,"power":0.0008},
  {"region":"Granada","site":"Melling VP","pol":"V","lat":0.944706901944842,"lng":-4.55461580210709E-02,"power":0.005},
  {"region":"Central","site":"Repton","pol":"V","lat":0.922085892567016,"lng":-2.69632257541498E-02,"power":0.008},
  {"region":"Central","site":"Rugeley","pol":"V","lat":0.920811231895409,"lng":-3.40291199860715E-02,"power":0.008},
  {"region":"Central","site":"Winshill","pol":"H","lat":0.921781669742572,"lng":-2.78753252274029E-02,"power":0.06},
  {"region":"Granada","site":"Lancaster","pol":"V","lat":0.944037172719272,"lng":-4.85195053086528E-02,"power":2},
  {"region":"Wales","site":"Llanarmon Yn Ial","pol":"V","lat":0.927029143779342,"lng":-5.59491051353633E-02,"power":0.002},
  {"region":"Wales","site":"Moel y Parc","pol":"H","lat":0.928880814617864,"lng":-5.78492907716085E-02,"power":20},
  {"region":"Wales","site":"Gronant","pol":"V","lat":0.930940787812692,"lng":-5.88300957378952E-02,"power":0.008},
  {"region":"Wales","site":"Prestatyn","pol":"V","lat":0.930758918597257,"lng":-5.92252405921915E-02,"power":0.025},
  {"region":"Wales","site":"Cefn Mawr","pol":"V","lat":0.924337162548657,"lng":-5.39591082017094E-02,"power":0.05},
  {"region":"Border","site":"Dentdale","pol":"V","lat":0.947089696654794,"lng":-4.22238019921424E-02,"power":0.0104},
  {"region":"Tyne Tees","site":"West Burton","pol":"V","lat":0.947497570560896,"lng":-3.41284816442326E-02,"power":0.0024},
  {"region":"Tyne Tees","site":"Bainbridge","pol":"V","lat":0.947696177496305,"lng":-0.036670602192276,"power":0.0076},
  {"region":"Wales","site":"Llangollen","pol":"V","lat":0.92451133235024,"lng":-0.05559565968928,"power":0.002},
  {"region":"Wales","site":"Pwll Glas","pol":"V","lat":0.926365346778185,"lng":-5.78846087133548E-02,"power":0.002},
  {"region":"Border","site":"Sedbergh","pol":"V","lat":0.94746659233296,"lng":-4.54474715673292E-02,"power":0.1},
  {"region":"Wales","site":"Glyn Ceiriog","pol":"V","lat":0.92396186236137,"lng":-5.56273832575441E-02,"power":0.002},
  {"region":"Central","site":"The Wrekin","pol":"H","lat":0.91927975735369,"lng":-4.45072815754732E-02,"power":20},
  {"region":"Wales","site":"Pontfadog","pol":"V","lat":0.923497087288743,"lng":-5.51864084853768E-02,"power":0.002},
  {"region":"Wales","site":"Glyndyfrdwy","pol":"V","lat":0.924627549195842,"lng":-0.056807564178479,"power":0.002},
  {"region":"Wales","site":"Cyffylliog","pol":"V","lat":0.926965355673447,"lng":-5.93396787485638E-02,"power":0.002},
  {"region":"Tyne Tees","site":"Whitaside","pol":"V","lat":0.94882776994934,"lng":-3.54754264421608E-02,"power":0.0025},
  {"region":"Border","site":"Millthrop","pol":"V","lat":0.948207064858807,"lng":-4.40869351878997E-02,"power":0.003},
  {"region":"Central","site":"Coalbrookdale","pol":"V","lat":0.91865069679073,"lng":-4.34059200012944E-02,"power":0.002},
  {"region":"Granada","site":"Cartmel","pol":"H","lat":0.946072670591484,"lng":-0.051645769763118,"power":0.002},
  {"region":"Central","site":"Ironbridge","pol":"V","lat":0.918496125980503,"lng":-4.32185581146027E-02,"power":0.0022},
  {"region":"Tyne Tees","site":"Grinton Lodge","pol":"V","lat":0.949003149006461,"lng":-0.033643261507287,"power":0.005},
  {"region":"Wales","site":"Pen y Banc","pol":"V","lat":0.925662841471016,"lng":-0.058956460303925,"power":0.004}
]
